notify_vocab/__init__.py
notify_vocab/get_words.py
notify_vocab/notification.py
notifyVocab-0.1.3.dist-info/LICENSE
notifyVocab-0.1.3.dist-info/METADATA
notifyVocab-0.1.3.dist-info/WHEEL
notifyVocab-0.1.3.dist-info/top_level.txt
notifyVocab-0.1.3.dist-info/RECORD
