Metadata-Version: 2.1
Name: notifyVocab
Version: 0.1.3
Summary: a small library that notifies you of a new word and its meaning every time you run it
Home-page: UNKNOWN
Author: Mohammad Tayyib
Author-email: tayyibsofi@gmail.com
License: UNKNOWN
Keywords: python,random-words,vocab,vocabulary,notification
Platform: UNKNOWN
Classifier: Development Status :: 1 - Planning
Classifier: Intended Audience :: Developers
Classifier: Programming Language :: Python :: 3
Classifier: Operating System :: Unix
Classifier: Operating System :: MacOS :: MacOS X
Classifier: Operating System :: Microsoft :: Windows
Requires-Dist: PyDictionary
Requires-Dist: plyer
